[
    {
        "type":"资质",
        "content":"新手"
    },{
        "type":"资质",
        "content":"资深干员"
    },{
        "type":"资质",
        "content":"高级资深干员"
    },{
        "type":"位置",
        "content":"远程位"
    },{
        "type":"位置",
        "content":"近战位"
    },{
        "type":"种类",
        "content":"先锋干员"
    },{
        "type":"种类",
        "content":"狙击干员"
    },{
        "type":"种类",
        "content":"医疗干员"
    },{
        "type":"种类",
        "content":"术师干员"
    },{
        "type":"种类",
        "content":"近卫干员"
    },{
        "type":"种类",
        "content":"重装干员"
    },{
        "type":"种类",
        "content":"辅助干员"
    },{
        "type":"种类",
        "content":"特种干员"
    },{
        "type":"词缀",
        "content":"治疗"
    },{
        "type":"词缀",
        "content":"支援"
    },{
        "type":"词缀",
        "content":"输出"
    },{
        "type":"词缀",
        "content":"群攻"
    },{
        "type":"词缀",
        "content":"减速"
    },{
        "type":"词缀",
        "content":"生存"
    },{
        "type":"词缀",
        "content":"防护"
    },{
        "type":"词缀",
        "content":"削弱"
    },{
        "type":"词缀",
        "content":"位移"
    },{
        "type":"词缀",
        "content":"控场"
    },{
        "type":"词缀",
        "content":"爆发"
    },{
        "type":"词缀",
        "content":"召唤"
    },{
        "type":"词缀",
        "content":"快速复活"
    },{
        "type":"词缀",
        "content":"费用回复"
    },{
        "type":"词缀",
        "content":"支援机械"
    }
]